MANIFEST.in
README.md
requirements.txt
setup.cfg
setup.py
smac/__init__.py
smac/__version__.py
smac/smac_cli.py
smac/configspace/__init__.py
smac/configspace/util.py
smac/epm/__init__.py
smac/epm/base_epm.py
smac/epm/base_imputor.py
smac/epm/random_epm.py
smac/epm/rf_with_instances.py
smac/epm/rfr_imputator.py
smac/epm/uncorrelated_mo_rf_with_instances.py
smac/facade/__init__.py
smac/facade/epils_facade.py
smac/facade/func_facade.py
smac/facade/roar_facade.py
smac/facade/smac_facade.py
smac/initial_design/__init__.py
smac/initial_design/default_configuration_design.py
smac/initial_design/initial_design.py
smac/initial_design/multi_config_initial_design.py
smac/initial_design/random_configuration_design.py
smac/initial_design/single_config_initial_design.py
smac/intensification/__init__.py
smac/intensification/intensification.py
smac/optimizer/__init__.py
smac/optimizer/acquisition.py
smac/optimizer/ei_optimization.py
smac/optimizer/epils.py
smac/optimizer/objective.py
smac/optimizer/pSMAC.py
smac/optimizer/smbo.py
smac/runhistory/__init__.py
smac/runhistory/runhistory.py
smac/runhistory/runhistory2epm.py
smac/scenario/__init__.py
smac/scenario/scenario.py
smac/stats/__init__.py
smac/stats/stats.py
smac/tae/__init__.py
smac/tae/execute_func.py
smac/tae/execute_ta_run.py
smac/tae/execute_ta_run_aclib.py
smac/tae/execute_ta_run_old.py
smac/utils/__init__.py
smac/utils/constants.py
smac/utils/duplicate_filter_logging.py
smac/utils/merge_foreign_data.py
smac/utils/test_helpers.py
smac/utils/util_funcs.py
smac/utils/validate.py
smac/utils/io/__init__.py
smac/utils/io/cmd_reader.py
smac/utils/io/input_reader.py
smac/utils/io/output_directory.py
smac/utils/io/output_writer.py
smac/utils/io/traj_logging.py
smac_nni.egg-info/PKG-INFO
smac_nni.egg-info/SOURCES.txt
smac_nni.egg-info/dependency_links.txt
smac_nni.egg-info/requires.txt
smac_nni.egg-info/top_level.txt
test/test_cli/__init__.py
test/test_cli/test_deterministic_smac.py
test/test_cli/test_restore_state.py
test/test_configspace/__init__.py
test/test_configspace/test_configspace.py
test/test_epm/__init__.py
test/test_epm/test_rfr_with_instances.py
