Metadata-Version: 1.1
Name: smac-nni
Version: 0.8.0
Summary: SMAC3, a Python implementation of 'Sequential Model-based Algorithm Configuration'.
Home-page: UNKNOWN
Author: Marius Lindauer, Matthias Feurer, Katharina Eggensperger, Aaron Klein, Stefan Falkner and Frank Hutter
Author-email: nni@microsoft.com
License: 3-clause BSD
Keywords: machine learning algorithm configuration hyperparameter optimization tuning
Platform: Linux
Classifier: Development Status :: 3 - Alpha
Classifier: Topic :: Utilities
Classifier: Topic :: Scientific/Engineering
Classifier: Topic :: Scientific/Engineering :: Artificial Intelligence
Classifier: License :: OSI Approved :: BSD License
